{
  "version": "2.2.0",
  "summary": {
    "title": "DFD Trinity Wallet",
    "owner": "",
    "description": "",
    "id": 0
  },
  "detail": {
    "contributors": [],
    "diagrams": [
      {
        "id": 0,
        "title": "New STRIDE diagram",
        "diagramType": "STRIDE",
        "placeholder": "New STRIDE diagram description",
        "thumbnail": "./public/content/images/thumbnail.stride.jpg",
        "version": "2.2.0",
        "cells": [
          {
            "position": {
              "x": 122.5,
              "y": 14
            },
            "size": {
              "width": 440,
              "height": 480
            },
            "shape": "trust-boundary-box",
            "attrs": {
              "headerText": {
                "text": "Trinity Wallet Application"
              }
            },
            "id": "24c52aa8-3a3e-4997-ab5f-f1755198ee72",
            "zIndex": -1,
            "data": {
              "type": "tm.BoundaryBox",
              "name": "Trinity Wallet Application",
              "description": "",
              "isTrustBoundary": true,
              "hasOpenThreats": false
            }
          },
          {
            "position": {
              "x": 164.99999999999915,
              "y": 259.0000000000001
            },
            "size": {
              "width": 120,
              "height": 220
            },
            "shape": "trust-boundary-box",
            "attrs": {
              "headerText": {
                "text": "Initiate Transactions"
              }
            },
            "id": "0b650d58-3880-4482-b045-5c43f894028b",
            "zIndex": -1,
            "data": {
              "type": "tm.BoundaryBox",
              "name": "Initiate Transactions",
              "description": "",
              "isTrustBoundary": true,
              "hasOpenThreats": false
            }
          },
          {
            "position": {
              "x": 340,
              "y": 299.0000000000001
            },
            "size": {
              "width": 170,
              "height": 170
            },
            "shape": "trust-boundary-box",
            "attrs": {
              "headerText": {
                "text": "Transaction Signing and Submission"
              }
            },
            "id": "941a0e47-8b05-4f99-8cfb-b697e064ceab",
            "zIndex": -1,
            "data": {
              "type": "tm.BoundaryBox",
              "name": "Transaction Signing and Submission",
              "description": "",
              "isTrustBoundary": true,
              "hasOpenThreats": false
            }
          },
          {
            "position": {
              "x": 600,
              "y": 259.0000000000003
            },
            "size": {
              "width": 220,
              "height": 240
            },
            "shape": "trust-boundary-box",
            "attrs": {
              "headerText": {
                "text": "Transaction status and Confirmation"
              }
            },
            "id": "ad46fb38-f909-4fb1-96be-91a5d7773541",
            "zIndex": -1,
            "data": {
              "type": "tm.BoundaryBox",
              "name": "Transaction status and Confirmation",
              "description": "",
              "isTrustBoundary": true,
              "hasOpenThreats": false
            }
          },
          {
            "position": {
              "x": 632,
              "y": 105.00000000000028
            },
            "size": {
              "width": 160,
              "height": 130
            },
            "shape": "trust-boundary-box",
            "attrs": {
              "headerText": {
                "text": "Other Actions"
              }
            },
            "id": "1cf4b8a3-a26c-4e34-b706-160ecb79fcc7",
            "zIndex": -1,
            "data": {
              "type": "tm.BoundaryBox",
              "name": "Other Actions",
              "description": "",
              "isTrustBoundary": true,
              "hasOpenThreats": false
            }
          },
          {
            "position": {
              "x": -10,
              "y": 134
            },
            "size": {
              "width": 112.5,
              "height": 60
            },
            "attrs": {
              "body": {
                "stroke": "#333333",
                "strokeWidth": 1.5,
                "strokeDasharray": null
              }
            },
            "visible": true,
            "shape": "actor",
            "id": "f8e2dd1c-a6b4-4f50-9849-752ae8a81272",
            "zIndex": 1,
            "data": {
              "type": "tm.Actor",
              "name": "Actor",
              "description": "",
              "outOfScope": false,
              "reasonOutOfScope": "",
              "hasOpenThreats": false,
              "providesAuthentication": false,
              "threats": []
            }
          },
          {
            "position": {
              "x": 224.99999999999915,
              "y": 74
            },
            "size": {
              "width": 60,
              "height": 60
            },
            "attrs": {
              "body": {
                "stroke": "#333333",
                "strokeWidth": 1.5,
                "strokeDasharray": null
              }
            },
            "visible": true,
            "shape": "process",
            "id": "8facf8a4-4ec9-4bcb-8842-3a527a25b4a5",
            "zIndex": 2,
            "data": {
              "type": "tm.Process",
              "name": "Process",
              "description": "",
              "outOfScope": false,
              "reasonOutOfScope": "",
              "hasOpenThreats": false,
              "handlesCardPayment": false,
              "handlesGoodsOrServices": false,
              "isWebApplication": false,
              "privilegeLevel": "",
              "threats": []
            }
          },
          {
            "shape": "flow",
            "attrs": {
              "line": {
                "stroke": "#333333",
                "targetMarker": {
                  "name": "block"
                },
                "sourceMarker": {
                  "name": ""
                },
                "strokeDasharray": null
              }
            },
            "width": 200,
            "height": 100,
            "zIndex": 10,
            "connector": "smooth",
            "data": {
              "type": "tm.Flow",
              "name": "Data Flow",
              "description": "",
              "outOfScope": false,
              "reasonOutOfScope": "",
              "hasOpenThreats": false,
              "isBidirectional": false,
              "isEncrypted": false,
              "isPublicNetwork": false,
              "protocol": "",
              "threats": []
            },
            "id": "2c7fe5e6-d984-428b-8e72-13824ae06dd7",
            "source": {
              "cell": "f8e2dd1c-a6b4-4f50-9849-752ae8a81272"
            },
            "target": {
              "cell": "8facf8a4-4ec9-4bcb-8842-3a527a25b4a5"
            },
            "vertices": [
              {
                "x": 100,
                "y": 107
              }
            ]
          },
          {
            "shape": "flow",
            "attrs": {
              "line": {
                "stroke": "#333333",
                "targetMarker": {
                  "name": "block"
                },
                "sourceMarker": {
                  "name": ""
                },
                "strokeDasharray": null
              }
            },
            "width": 200,
            "height": 100,
            "zIndex": 10,
            "connector": "smooth",
            "data": {
              "type": "tm.Flow",
              "name": "Data Flow",
              "description": "",
              "outOfScope": false,
              "reasonOutOfScope": "",
              "hasOpenThreats": false,
              "isBidirectional": false,
              "isEncrypted": false,
              "isPublicNetwork": false,
              "protocol": "",
              "threats": []
            },
            "id": "8ece9737-b5da-470c-a6d4-24289b90a4b5",
            "source": {
              "x": 285,
              "y": 94
            },
            "target": {
              "cell": "48a7c366-5208-4325-9743-61c2f728082d"
            },
            "vertices": [
              {
                "x": 440,
                "y": 70
              }
            ]
          },
          {
            "shape": "flow",
            "attrs": {
              "line": {
                "stroke": "#333333",
                "targetMarker": {
                  "name": "block"
                },
                "sourceMarker": {
                  "name": ""
                },
                "strokeDasharray": null
              }
            },
            "width": 200,
            "height": 100,
            "zIndex": 10,
            "connector": "smooth",
            "data": {
              "type": "tm.Flow",
              "name": "Data Flow",
              "description": "",
              "outOfScope": false,
              "reasonOutOfScope": "",
              "hasOpenThreats": false,
              "isBidirectional": false,
              "isEncrypted": false,
              "isPublicNetwork": false,
              "protocol": "",
              "threats": []
            },
            "id": "0ec7b4a9-64a4-4948-bed9-1ad7debd78fe",
            "source": {
              "cell": "48a7c366-5208-4325-9743-61c2f728082d"
            },
            "target": {
              "cell": "d5d02419-9e45-453f-8b37-6682ee76a2f0"
            },
            "vertices": [
              {
                "x": 520,
                "y": 80
              },
              {
                "x": 440,
                "y": 110
              }
            ]
          },
          {
            "shape": "flow",
            "attrs": {
              "line": {
                "stroke": "#333333",
                "targetMarker": {
                  "name": "block"
                },
                "sourceMarker": {
                  "name": ""
                },
                "strokeDasharray": null
              }
            },
            "width": 200,
            "height": 100,
            "zIndex": 10,
            "connector": "smooth",
            "data": {
              "type": "tm.Flow",
              "name": "Data Flow",
              "description": "",
              "outOfScope": false,
              "reasonOutOfScope": "",
              "hasOpenThreats": false,
              "isBidirectional": false,
              "isEncrypted": false,
              "isPublicNetwork": false,
              "protocol": "",
              "threats": []
            },
            "id": "6d5defc6-bf55-4648-bccb-679e034b7d02",
            "source": {
              "cell": "d5d02419-9e45-453f-8b37-6682ee76a2f0"
            },
            "target": {
              "cell": "9c33b147-7222-46c5-97f8-b5ea6029c023"
            }
          },
          {
            "shape": "flow",
            "attrs": {
              "line": {
                "stroke": "#333333",
                "targetMarker": {
                  "name": "block"
                },
                "sourceMarker": {
                  "name": ""
                },
                "strokeDasharray": null
              }
            },
            "width": 200,
            "height": 100,
            "zIndex": 10,
            "connector": "smooth",
            "data": {
              "type": "tm.Flow",
              "name": "Data Flow",
              "description": "",
              "outOfScope": false,
              "reasonOutOfScope": "",
              "hasOpenThreats": false,
              "isBidirectional": false,
              "isEncrypted": false,
              "isPublicNetwork": false,
              "protocol": "",
              "threats": []
            },
            "id": "d8153714-4a06-44fb-8921-04d394e09343",
            "source": {
              "x": 225,
              "y": 204
            },
            "target": {
              "cell": "10c0036e-68b1-4183-97ae-1efc29bc2074"
            },
            "vertices": [
              {
                "x": 290,
                "y": 204
              }
            ]
          },
          {
            "shape": "flow",
            "attrs": {
              "line": {
                "stroke": "#333333",
                "targetMarker": {
                  "name": "block"
                },
                "sourceMarker": {
                  "name": ""
                },
                "strokeDasharray": null
              }
            },
            "width": 200,
            "height": 100,
            "zIndex": 10,
            "connector": "smooth",
            "data": {
              "type": "tm.Flow",
              "name": "Data Flow",
              "description": "",
              "outOfScope": false,
              "reasonOutOfScope": "",
              "hasOpenThreats": false,
              "isBidirectional": false,
              "isEncrypted": false,
              "isPublicNetwork": false,
              "protocol": "",
              "threats": []
            },
            "id": "c9621562-9bea-430d-b646-ea468c83ecca",
            "source": {
              "cell": "10c0036e-68b1-4183-97ae-1efc29bc2074"
            },
            "target": {
              "cell": "ec8ba83e-7d6a-42bc-9ca4-df843d0f93c9"
            }
          },
          {
            "shape": "flow",
            "attrs": {
              "line": {
                "stroke": "#333333",
                "targetMarker": {
                  "name": "block"
                },
                "sourceMarker": {
                  "name": ""
                },
                "strokeDasharray": null
              }
            },
            "width": 200,
            "height": 100,
            "zIndex": 10,
            "connector": "smooth",
            "data": {
              "type": "tm.Flow",
              "name": "Data Flow",
              "description": "",
              "outOfScope": false,
              "reasonOutOfScope": "",
              "hasOpenThreats": false,
              "isBidirectional": false,
              "isEncrypted": false,
              "isPublicNetwork": false,
              "protocol": "",
              "threats": []
            },
            "id": "4189adf2-fe1a-4f0a-98ad-f1bef3c042e7",
            "source": {
              "cell": "ec8ba83e-7d6a-42bc-9ca4-df843d0f93c9"
            },
            "target": {
              "cell": "f79d6fcf-b749-47a8-94da-efd10f2b9430"
            },
            "vertices": [
              {
                "x": 227.36,
                "y": 350
              }
            ]
          },
          {
            "shape": "flow",
            "attrs": {
              "line": {
                "stroke": "#333333",
                "targetMarker": {
                  "name": "block"
                },
                "sourceMarker": {
                  "name": ""
                },
                "strokeDasharray": null
              }
            },
            "width": 200,
            "height": 100,
            "zIndex": 10,
            "connector": "smooth",
            "data": {
              "type": "tm.Flow",
              "name": "Data Flow",
              "description": "",
              "outOfScope": false,
              "reasonOutOfScope": "",
              "hasOpenThreats": false,
              "isBidirectional": false,
              "isEncrypted": false,
              "isPublicNetwork": false,
              "protocol": "",
              "threats": []
            },
            "id": "2ce6991a-d736-4f0b-98f2-9feabbc92f35",
            "source": {
              "x": 245,
              "y": 409
            },
            "target": {
              "cell": "d5f47587-45e9-4f0d-a6a4-07ab57f0c3d4"
            },
            "vertices": [
              {
                "x": 290,
                "y": 361.5
              }
            ]
          },
          {
            "shape": "flow",
            "attrs": {
              "line": {
                "stroke": "#333333",
                "targetMarker": {
                  "name": "block"
                },
                "sourceMarker": {
                  "name": ""
                },
                "strokeDasharray": null
              }
            },
            "width": 200,
            "height": 100,
            "zIndex": 10,
            "connector": "smooth",
            "data": {
              "type": "tm.Flow",
              "name": "Data Flow",
              "description": "",
              "outOfScope": false,
              "reasonOutOfScope": "",
              "hasOpenThreats": false,
              "isBidirectional": false,
              "isEncrypted": false,
              "isPublicNetwork": false,
              "protocol": "",
              "threats": []
            },
            "id": "e1339aa2-dd1b-4cf4-ab08-372de8eb9dc5",
            "source": {
              "x": 400,
              "y": 354
            },
            "target": {
              "cell": "adeefcba-b906-46b5-b45b-eada6502ad55"
            }
          },
          {
            "shape": "flow",
            "attrs": {
              "line": {
                "stroke": "#333333",
                "targetMarker": {
                  "name": "block"
                },
                "sourceMarker": {
                  "name": ""
                },
                "strokeDasharray": null
              }
            },
            "width": 200,
            "height": 100,
            "zIndex": 10,
            "connector": "smooth",
            "data": {
              "type": "tm.Flow",
              "name": "Data Flow",
              "description": "",
              "outOfScope": false,
              "reasonOutOfScope": "",
              "hasOpenThreats": false,
              "isBidirectional": false,
              "isEncrypted": false,
              "isPublicNetwork": false,
              "protocol": "",
              "threats": []
            },
            "id": "2f20cb9e-24c1-49c1-b38f-677a65a52e24",
            "source": {
              "x": 459,
              "y": 409
            },
            "target": {
              "cell": "abff7628-40aa-4579-9e9e-10f9a935cf98"
            }
          },
          {
            "shape": "flow",
            "attrs": {
              "line": {
                "stroke": "#333333",
                "targetMarker": {
                  "name": "block"
                },
                "sourceMarker": {
                  "name": ""
                },
                "strokeDasharray": null
              }
            },
            "width": 200,
            "height": 100,
            "zIndex": 10,
            "connector": "smooth",
            "data": {
              "type": "tm.Flow",
              "name": "Data Flow",
              "description": "",
              "outOfScope": false,
              "reasonOutOfScope": "",
              "hasOpenThreats": false,
              "isBidirectional": false,
              "isEncrypted": false,
              "isPublicNetwork": false,
              "protocol": "",
              "threats": []
            },
            "id": "50d9add1-ce1e-462f-9fdf-822884ab98e3",
            "source": {
              "cell": "abff7628-40aa-4579-9e9e-10f9a935cf98"
            },
            "target": {
              "cell": "9791d573-c82d-4faf-bb04-a1165b9d189e"
            },
            "vertices": [
              {
                "x": 690,
                "y": 430
              }
            ]
          },
          {
            "shape": "flow",
            "attrs": {
              "line": {
                "stroke": "#333333",
                "targetMarker": {
                  "name": "block"
                },
                "sourceMarker": {
                  "name": ""
                },
                "strokeDasharray": null
              }
            },
            "width": 200,
            "height": 100,
            "zIndex": 10,
            "connector": "smooth",
            "data": {
              "type": "tm.Flow",
              "name": "Data Flow",
              "description": "",
              "outOfScope": false,
              "reasonOutOfScope": "",
              "hasOpenThreats": false,
              "isBidirectional": false,
              "isEncrypted": false,
              "isPublicNetwork": false,
              "protocol": "",
              "threats": []
            },
            "id": "4b2f5061-1407-4740-ab71-2cb3d6399acc",
            "source": {
              "x": 724,
              "y": 434
            },
            "target": {
              "cell": "8346a347-f07b-4228-8e69-2f30f06575fa"
            }
          },
          {
            "shape": "flow",
            "attrs": {
              "line": {
                "stroke": "#333333",
                "targetMarker": {
                  "name": "block"
                },
                "sourceMarker": {
                  "name": ""
                },
                "strokeDasharray": null
              }
            },
            "width": 200,
            "height": 100,
            "zIndex": 10,
            "connector": "smooth",
            "data": {
              "type": "tm.Flow",
              "name": "Data Flow",
              "description": "",
              "outOfScope": false,
              "reasonOutOfScope": "",
              "hasOpenThreats": false,
              "isBidirectional": false,
              "isEncrypted": false,
              "isPublicNetwork": false,
              "protocol": "",
              "threats": []
            },
            "id": "6ccdbeb5-2636-4204-9b36-65cf4258d6c5",
            "source": {
              "cell": "79e73bf2-f888-4bc9-93c6-8976ca740a8e"
            },
            "target": {
              "x": 720,
              "y": 260
            }
          },
          {
            "position": {
              "x": 620,
              "y": 14
            },
            "size": {
              "width": 120,
              "height": 60
            },
            "attrs": {
              "topLine": {
                "strokeWidth": 1.5,
                "strokeDasharray": null
              },
              "bottomLine": {
                "strokeWidth": 1.5,
                "strokeDasharray": null
              }
            },
            "visible": true,
            "shape": "store",
            "id": "48a7c366-5208-4325-9743-61c2f728082d",
            "zIndex": 11,
            "data": {
              "type": "tm.Store",
              "name": "Store",
              "description": "",
              "outOfScope": false,
              "reasonOutOfScope": "",
              "hasOpenThreats": false,
              "isALog": false,
              "isEncrypted": false,
              "isSigned": false,
              "storesCredentials": false,
              "storesInventory": false,
              "threats": []
            }
          },
          {
            "position": {
              "x": 340,
              "y": 105
            },
            "size": {
              "width": 60,
              "height": 60
            },
            "attrs": {
              "body": {
                "stroke": "#333333",
                "strokeWidth": 1.5,
                "strokeDasharray": null
              }
            },
            "visible": true,
            "shape": "process",
            "id": "d5d02419-9e45-453f-8b37-6682ee76a2f0",
            "zIndex": 12,
            "data": {
              "type": "tm.Process",
              "name": "Process",
              "description": "",
              "outOfScope": false,
              "reasonOutOfScope": "",
              "hasOpenThreats": false,
              "handlesCardPayment": false,
              "handlesGoodsOrServices": false,
              "isWebApplication": false,
              "privilegeLevel": "",
              "threats": []
            }
          },
          {
            "position": {
              "x": 204.99999999999915,
              "y": 165
            },
            "size": {
              "width": 50,
              "height": 50
            },
            "attrs": {
              "topLine": {
                "strokeWidth": 1.5,
                "strokeDasharray": null
              },
              "bottomLine": {
                "strokeWidth": 1.5,
                "strokeDasharray": null
              }
            },
            "visible": true,
            "shape": "store",
            "id": "9c33b147-7222-46c5-97f8-b5ea6029c023",
            "zIndex": 13,
            "data": {
              "type": "tm.Store",
              "name": "Store",
              "description": "",
              "outOfScope": false,
              "reasonOutOfScope": "",
              "hasOpenThreats": false,
              "isALog": false,
              "isEncrypted": false,
              "isSigned": false,
              "storesCredentials": false,
              "storesInventory": false,
              "threats": []
            }
          },
          {
            "position": {
              "x": 365,
              "y": 224
            },
            "size": {
              "width": 60,
              "height": 60
            },
            "attrs": {
              "body": {
                "stroke": "#333333",
                "strokeWidth": 1.5,
                "strokeDasharray": null
              }
            },
            "visible": true,
            "shape": "process",
            "id": "10c0036e-68b1-4183-97ae-1efc29bc2074",
            "zIndex": 14,
            "data": {
              "type": "tm.Process",
              "name": "Process",
              "description": "",
              "outOfScope": false,
              "reasonOutOfScope": "",
              "hasOpenThreats": false,
              "handlesCardPayment": false,
              "handlesGoodsOrServices": false,
              "isWebApplication": false,
              "privilegeLevel": "",
              "threats": []
            }
          },
          {
            "position": {
              "x": 204.99999999999915,
              "y": 284
            },
            "size": {
              "width": 50,
              "height": 50
            },
            "attrs": {
              "body": {
                "stroke": "#333333",
                "strokeWidth": 1.5,
                "strokeDasharray": null
              }
            },
            "visible": true,
            "shape": "process",
            "id": "ec8ba83e-7d6a-42bc-9ca4-df843d0f93c9",
            "zIndex": 15,
            "data": {
              "type": "tm.Process",
              "name": "Process",
              "description": "",
              "outOfScope": false,
              "reasonOutOfScope": "",
              "hasOpenThreats": false,
              "handlesCardPayment": false,
              "handlesGoodsOrServices": false,
              "isWebApplication": false,
              "privilegeLevel": "",
              "threats": []
            }
          },
          {
            "position": {
              "x": 199.99999999999915,
              "y": 390
            },
            "size": {
              "width": 50,
              "height": 50
            },
            "attrs": {
              "body": {
                "stroke": "#333333",
                "strokeWidth": 1.5,
                "strokeDasharray": null
              }
            },
            "visible": true,
            "shape": "process",
            "id": "f79d6fcf-b749-47a8-94da-efd10f2b9430",
            "zIndex": 16,
            "data": {
              "type": "tm.Process",
              "name": "Process",
              "description": "",
              "outOfScope": false,
              "reasonOutOfScope": "",
              "hasOpenThreats": false,
              "handlesCardPayment": false,
              "handlesGoodsOrServices": false,
              "isWebApplication": false,
              "privilegeLevel": "",
              "threats": []
            }
          },
          {
            "position": {
              "x": 370,
              "y": 334
            },
            "size": {
              "width": 50,
              "height": 50
            },
            "attrs": {
              "body": {
                "stroke": "#333333",
                "strokeWidth": 1.5,
                "strokeDasharray": null
              }
            },
            "visible": true,
            "shape": "process",
            "id": "d5f47587-45e9-4f0d-a6a4-07ab57f0c3d4",
            "zIndex": 17,
            "data": {
              "type": "tm.Process",
              "name": "Process",
              "description": "",
              "outOfScope": false,
              "reasonOutOfScope": "",
              "hasOpenThreats": false,
              "handlesCardPayment": false,
              "handlesGoodsOrServices": false,
              "isWebApplication": false,
              "privilegeLevel": "",
              "threats": []
            }
          },
          {
            "position": {
              "x": 425,
              "y": 390
            },
            "size": {
              "width": 50,
              "height": 50
            },
            "attrs": {
              "body": {
                "stroke": "#333333",
                "strokeWidth": 1.5,
                "strokeDasharray": null
              }
            },
            "visible": true,
            "shape": "process",
            "id": "adeefcba-b906-46b5-b45b-eada6502ad55",
            "zIndex": 18,
            "data": {
              "type": "tm.Process",
              "name": "Process",
              "description": "",
              "outOfScope": false,
              "reasonOutOfScope": "",
              "hasOpenThreats": false,
              "handlesCardPayment": false,
              "handlesGoodsOrServices": false,
              "isWebApplication": false,
              "privilegeLevel": "",
              "threats": []
            }
          },
          {
            "position": {
              "x": 620,
              "y": 366
            },
            "size": {
              "width": 60,
              "height": 60
            },
            "attrs": {
              "body": {
                "stroke": "#333333",
                "strokeWidth": 1.5,
                "strokeDasharray": null
              }
            },
            "visible": true,
            "shape": "process",
            "id": "abff7628-40aa-4579-9e9e-10f9a935cf98",
            "zIndex": 19,
            "data": {
              "type": "tm.Process",
              "name": "Process",
              "description": "",
              "outOfScope": false,
              "reasonOutOfScope": "",
              "hasOpenThreats": false,
              "handlesCardPayment": false,
              "handlesGoodsOrServices": false,
              "isWebApplication": false,
              "privilegeLevel": "",
              "threats": []
            }
          },
          {
            "position": {
              "x": 700,
              "y": 419.0000000000001
            },
            "size": {
              "width": 60,
              "height": 60
            },
            "attrs": {
              "body": {
                "stroke": "#333333",
                "strokeWidth": 1.5,
                "strokeDasharray": null
              }
            },
            "visible": true,
            "shape": "process",
            "id": "9791d573-c82d-4faf-bb04-a1165b9d189e",
            "zIndex": 20,
            "data": {
              "type": "tm.Process",
              "name": "Process",
              "description": "",
              "outOfScope": false,
              "reasonOutOfScope": "",
              "hasOpenThreats": false,
              "handlesCardPayment": false,
              "handlesGoodsOrServices": false,
              "isWebApplication": false,
              "privilegeLevel": "",
              "threats": []
            }
          },
          {
            "position": {
              "x": 730,
              "y": 284
            },
            "size": {
              "width": 60,
              "height": 60
            },
            "attrs": {
              "body": {
                "stroke": "#333333",
                "strokeWidth": 1.5,
                "strokeDasharray": null
              }
            },
            "visible": true,
            "shape": "process",
            "id": "8346a347-f07b-4228-8e69-2f30f06575fa",
            "zIndex": 21,
            "data": {
              "type": "tm.Process",
              "name": "Process",
              "description": "",
              "outOfScope": false,
              "reasonOutOfScope": "",
              "hasOpenThreats": false,
              "handlesCardPayment": false,
              "handlesGoodsOrServices": false,
              "isWebApplication": false,
              "privilegeLevel": "",
              "threats": []
            }
          },
          {
            "position": {
              "x": 682,
              "y": 134
            },
            "size": {
              "width": 60,
              "height": 60
            },
            "attrs": {
              "body": {
                "stroke": "#333333",
                "strokeWidth": 1.5,
                "strokeDasharray": null
              }
            },
            "visible": true,
            "shape": "process",
            "id": "79e73bf2-f888-4bc9-93c6-8976ca740a8e",
            "zIndex": 22,
            "data": {
              "type": "tm.Process",
              "name": "Process",
              "description": "",
              "outOfScope": false,
              "reasonOutOfScope": "",
              "hasOpenThreats": false,
              "handlesCardPayment": false,
              "handlesGoodsOrServices": false,
              "isWebApplication": false,
              "privilegeLevel": "",
              "threats": []
            }
          }
        ]
      }
    ],
    "diagramTop": 2,
    "reviewer": "",
    "threatTop": 0
  }
}